README.md
setup.py
py_extract/__init__.py
py_extract/helpers.py
py_extract/video_tools.py
py_extract.egg-info/PKG-INFO
py_extract.egg-info/SOURCES.txt
py_extract.egg-info/dependency_links.txt
py_extract.egg-info/requires.txt
py_extract.egg-info/top_level.txt