Metadata-Version: 2.1
Name: py-extract
Version: 0.0.4
Summary: Py_extract is a simple, light-weight python library to handle some extraction tasks using less lines of code.
Home-page: https://github.com/Itz-fork/py-extract
Author: Itz-fork
Author-email: itz-fork@users.noreply.github.com
License: MIT
Download-URL: https://github.com/Itz-fork/py-extract
Keywords: python,extract,py-extract
Platform: UNKNOWN
Classifier: Development Status :: 4 - Beta
Classifier: Intended Audience :: Developers
Classifier: Topic :: Multimedia
Classifier: License :: OSI Approved :: MIT License
Classifier: Programming Language :: Python :: 3
Classifier: Programming Language :: Python :: 3.4
Classifier: Programming Language :: Python :: 3.5
Classifier: Programming Language :: Python :: 3.6
Classifier: Programming Language :: Python :: 3.9
